alignment_train_cpu_binding.cpython-312-x86_64-linux-gnu.so
fairseq/checkpoint_utils.py
fairseq/version.py
fairseq/hub_utils.py
fairseq/token_generation_constraints.py
fairseq/pdb.py
fairseq/registry.py
fairseq/libbleu.cpython-312-x86_64-linux-gnu.so
fairseq/speech_generator.py
fairseq/ngram_repeat_block.py
fairseq/libbase.cpython-312-x86_64-linux-gnu.so
fairseq/tokenizer.py
fairseq/file_io.py
fairseq/file_chunker_utils.py
fairseq/nan_detector.py
fairseq/utils.py
fairseq/options.py
fairseq/iterative_refinement_generator.py
fairseq/sequence_scorer.py
fairseq/quantization_utils.py
fairseq/trainer.py
fairseq/search.py
fairseq/__init__.py
fairseq/file_utils.py
fairseq/sequence_generator.py
fairseq/libnat.cpython-312-x86_64-linux-gnu.so
fairseq/binarizer.py
fairseq/incremental_decoding_utils.py
fairseq/examples/__init__.py
fairseq/examples/.gitignore
fairseq/examples/linformer/README.md
fairseq/examples/linformer/linformer_src/__init__.py
fairseq/examples/linformer/linformer_src/models/__init__.py
fairseq/examples/linformer/linformer_src/models/linformer_roberta.py
fairseq/examples/linformer/linformer_src/modules/multihead_linear_attention.py
fairseq/examples/linformer/linformer_src/modules/__init__.py
fairseq/examples/linformer/linformer_src/modules/linformer_sentence_encoder.py
fairseq/examples/linformer/linformer_src/modules/linformer_sentence_encoder_layer.py
fairseq/examples/pointer_generator/README.md
fairseq/examples/pointer_generator/postprocess.py
fairseq/examples/pointer_generator/preprocess.py
fairseq/examples/pointer_generator/README.xsum.md
fairseq/examples/pointer_generator/pointer_generator_src/__init__.py
fairseq/examples/pointer_generator/pointer_generator_src/transformer_pg.py
fairseq/examples/speech_recognition/README.md
fairseq/examples/speech_recognition/w2l_decoder.py
fairseq/examples/speech_recognition/infer.py
fairseq/examples/speech_recognition/__init__.py
fairseq_fixed-0.12.3.1.dist-info/METADATA
fairseq_fixed-0.12.3.1.dist-info/entry_points.txt
fairseq_fixed-0.12.3.1.dist-info/LICENSE
fairseq_fixed-0.12.3.1.dist-info/RECORD
fairseq_fixed-0.12.3.1.dist-info/WHEEL
fairseq_fixed-0.12.3.1.dist-info/top_level.txt
