Metadata-Version: 2.1
Name: fairseq-fixed
Version: 0.12.3.1
Summary: Facebook AI Research Sequence-to-Sequence Toolkit -- Now Supporting Python 3.11+
Home-page: https://github.com/JackismyShephard/fairseq
Classifier: Intended Audience :: Science/Research
Classifier: License :: OSI Approved :: MIT License
Classifier: Programming Language :: Python :: 3.11
Classifier: Programming Language :: Python :: 3.12
Classifier: Topic :: Scientific/Engineering :: Artificial Intelligence
License-File: LICENSE
Requires-Dist: cffi
Requires-Dist: cython
Requires-Dist: hydra-core ==1.3.2
Requires-Dist: omegaconf ==2.3.0
Requires-Dist: numpy >=1.21.3
Requires-Dist: regex
Requires-Dist: sacrebleu >=1.4.12
Requires-Dist: torch >=1.13
Requires-Dist: tqdm
Requires-Dist: bitarray
Requires-Dist: torchaudio >=0.8.0
Requires-Dist: scikit-learn
Requires-Dist: packaging
Provides-Extra: dev
Requires-Dist: flake8 ; extra == 'dev'
Requires-Dist: pytest ; extra == 'dev'
Requires-Dist: black ==22.3.0 ; extra == 'dev'
Provides-Extra: docs
Requires-Dist: sphinx ; extra == 'docs'
Requires-Dist: sphinx-argparse ; extra == 'docs'
